{
  "2018 Putnam B Problems/Problem 1": {
    "parse": {
      "title": "2018 Putnam B Problems/Problem 1",
      "pageid": 17489,
      "revid": 105442,
      "text": {
        "*": "<div class=\"mw-parser-output\"><h2><span class=\"mw-headline\" id=\"Problem\">Problem</span><span class=\"mw-editsection\"><span class=\"mw-editsection-bracket\">[</span><a href=\"/wiki/index.php?title=2018_Putnam_B_Problems/Problem_1&amp;action=edit&amp;section=1\" title=\"Edit section: Problem\">edit</a><span class=\"mw-editsection-bracket\">]</span></span></h2>\n<p>Let <img src=\"//latex.artofproblemsolving.com/7/4/f/74f4008768812f46db4b252c9e69cf98c5faaa4b.png\" class=\"latex\" alt=\"$\\mathcal{P}$\" style=\"vertical-align: -1px\" width=\"13\" height=\"14\" /> be the set of vectors defined by\n<img src=\"//latex.artofproblemsolving.com/b/4/5/b4565d582b99ce2ad0598541bf807376bb532d3c.png\" class=\"latexcenter\" alt=\"\\[\\mathcal{P} = \\left\\{\\begin{pmatrix} a \\\\ b \\end{pmatrix} \\, \\middle\\vert \\, 0 \\le a \\le 2, 0 \\le b \\le 100, \\, \\text{and} \\, a, b \\in \\mathbb{Z}\\right\\}.\\]\" width=\"396\" height=\"43\" />Find all <img src=\"//latex.artofproblemsolving.com/2/5/2/252bd4b520279b38755b7b1f0ab97ab4d2f28d75.png\" class=\"latex\" alt=\"$\\mathbf{v} \\in \\mathcal{P}$\" style=\"vertical-align: -1px\" width=\"47\" height=\"14\" /> such that the set <img src=\"//latex.artofproblemsolving.com/2/1/2/212337fbb0c59c53878867f76bf32232f64da004.png\" class=\"latex\" alt=\"$\\mathcal{P}\\setminus\\{\\mathbf{v}\\}$\" style=\"vertical-align: -4px\" width=\"59\" height=\"18\" /> obtained by omitting vector <img src=\"//latex.artofproblemsolving.com/1/c/3/1c39926efbcdc7d77c9337f5d48dd8e1761aec2d.png\" class=\"latex\" alt=\"$\\mathbf{v}$\" width=\"11\" height=\"9\" /> from <img src=\"//latex.artofproblemsolving.com/7/4/f/74f4008768812f46db4b252c9e69cf98c5faaa4b.png\" class=\"latex\" alt=\"$\\mathcal{P}$\" style=\"vertical-align: -1px\" width=\"13\" height=\"14\" /> can be partitioned into two sets of equal size and equal sum.\n</p>\n<h2><span class=\"mw-headline\" id=\"Solution\">Solution</span><span class=\"mw-editsection\"><span class=\"mw-editsection-bracket\">[</span><a href=\"/wiki/index.php?title=2018_Putnam_B_Problems/Problem_1&amp;action=edit&amp;section=2\" title=\"Edit section: Solution\">edit</a><span class=\"mw-editsection-bracket\">]</span></span></h2>\n<p>The problems on this page are copyrighted by the <a rel=\"nofollow\" class=\"external text\" href=\"http://www.maa.org\">Mathematical Association of America</a>'s <a rel=\"nofollow\" class=\"external text\" href=\"https://maa.org/student-programs/amc/\">American Mathematics Competitions</a>. <a href=\"/wiki/index.php/File:AMC_logo.png\" class=\"image\"><img alt=\"AMC logo.png\" src=\"https://wiki-images.artofproblemsolving.com//8/8b/AMC_logo.png\" width=\"97\" height=\"84\" style=\"vertical-align: middle\" /></a>\n</p>\n<div style=\"clear:both;\"></div>\n\n<!-- \nNewPP limit report\nCached time: 20240907180915\nCache expiry: 86400\nDynamic content: false\nCPU time usage: 0.030 seconds\nReal time usage: 0.031 seconds\nPreprocessor visited node count: 63/1000000\nPreprocessor generated node count: 144/1000000\nPost‐expand include size: 243/2097152 bytes\nTemplate argument size: 0/2097152 bytes\nHighest expansion depth: 2/40\nExpensive parser function count: 0/100\nUnstrip recursion depth: 0/20\nUnstrip post‐expand size: 1218/5000000 bytes\n-->\n<!--\nTransclusion expansion time report (%,ms,calls,template)\n100.00%    1.001      1 Template:MAA_Notice\n100.00%    1.001      1 -total\n-->\n</div>\n<!-- Saved in parser cache with key wiki-wiki_:pcache:idhash:17489-0!canonical and timestamp 20240907180915 and revision id 105442\n -->\n"
      },
      "langlinks": [],
      "categories": [],
      "links": [],
      "templates": [
        {
          "ns": 10,
          "exists": "",
          "*": "Template:MAA Notice"
        }
      ],
      "images": [
        "AMC_logo.png"
      ],
      "externallinks": [
        "http://www.maa.org",
        "https://maa.org/student-programs/amc/"
      ],
      "sections": [
        {
          "toclevel": 1,
          "level": "2",
          "line": "Problem",
          "number": "1",
          "index": "1",
          "fromtitle": "2018_Putnam_B_Problems/Problem_1",
          "byteoffset": 0,
          "anchor": "Problem"
        },
        {
          "toclevel": 1,
          "level": "2",
          "line": "Solution",
          "number": "2",
          "index": "2",
          "fromtitle": "2018_Putnam_B_Problems/Problem_1",
          "byteoffset": 503,
          "anchor": "Solution"
        }
      ],
      "parsewarnings": [],
      "displaytitle": "2018 Putnam B Problems/Problem 1",
      "iwlinks": [],
      "properties": []
    }
  }
}